{
  "address": "25DPjpkgYRoDq1fjCktycLQDCWt4jHfKWXPVp6SaC2Gk",
  "metadata": {
    "name": "kirasub",
    "version": "0.1.0",
    "spec": "0.1.0",
    "description": "Created with Anchor"
  },
  "instructions": [
    {
      "name": "create_plan",
      "discriminator": [
        77,
        43,
        141,
        254,
        212,
        118,
        41,
        186
      ],
      "accounts": [
        {
          "name": "merchant_config",
          "writable": true,
          "pda": {
            "seeds": [
              {
                "kind": "const",
                "value": [
                  109,
                  101,
                  114,
                  99,
                  104,
                  97,
                  110,
                  116
                ]
              },
              {
                "kind": "account",
                "path": "authority"
              }
            ]
          }
        },
        {
          "name": "plan",
          "writable": true,
          "pda": {
            "seeds": [
              {
                "kind": "const",
                "value": [
                  112,
                  108,
                  97,
                  110
                ]
              },
              {
                "kind": "account",
                "path": "merchant_config"
              },
              {
                "kind": "arg",
                "path": "plan_id"
              }
            ]
          }
        },
        {
          "name": "authority",
          "writable": true,
          "signer": true,
          "relations": [
            "merchant_config"
          ]
        },
        {
          "name": "system_program",
          "address": "11111111111111111111111111111111"
        }
      ],
      "args": [
        {
          "name": "plan_id",
          "type": "u64"
        },
        {
          "name": "name",
          "type": "string"
        },
        {
          "name": "price_usd_cents",
          "type": "u64"
        },
        {
          "name": "period_days",
          "type": "u16"
        }
      ]
    },
    {
      "name": "grant_entitlement",
      "discriminator": [
        4,
        8,
        68,
        80,
        43,
        40,
        29,
        151
      ],
      "accounts": [
        {
          "name": "merchant_config",
          "pda": {
            "seeds": [
              {
                "kind": "const",
                "value": [
                  109,
                  101,
                  114,
                  99,
                  104,
                  97,
                  110,
                  116
                ]
              },
              {
                "kind": "account",
                "path": "authority"
              }
            ]
          }
        },
        {
          "name": "plan",
          "pda": {
            "seeds": [
              {
                "kind": "const",
                "value": [
                  112,
                  108,
                  97,
                  110
                ]
              },
              {
                "kind": "account",
                "path": "merchant_config"
              },
              {
                "kind": "account",
                "path": "plan.plan_id",
                "account": "Plan"
              }
            ]
          }
        },
        {
          "name": "entitlement",
          "writable": true,
          "pda": {
            "seeds": [
              {
                "kind": "const",
                "value": [
                  101,
                  110,
                  116,
                  105,
                  116,
                  108,
                  101,
                  109,
                  101,
                  110,
                  116
                ]
              },
              {
                "kind": "account",
                "path": "merchant_config"
              },
              {
                "kind": "account",
                "path": "plan.plan_id",
                "account": "Plan"
              },
              {
                "kind": "account",
                "path": "subscriber"
              }
            ]
          }
        },
        {
          "name": "subscriber"
        },
        {
          "name": "authority",
          "writable": true,
          "signer": true,
          "relations": [
            "merchant_config"
          ]
        },
        {
          "name": "system_program",
          "address": "11111111111111111111111111111111"
        }
      ],
      "args": [
        {
          "name": "payment_reference_hash",
          "type": {
            "array": [
              "u8",
              32
            ]
          }
        },
        {
          "name": "amount_usd_cents",
          "type": "u64"
        }
      ]
    },
    {
      "name": "initialize_merchant",
      "discriminator": [
        7,
        90,
        74,
        38,
        99,
        111,
        142,
        77
      ],
      "accounts": [
        {
          "name": "merchant_config",
          "writable": true,
          "pda": {
            "seeds": [
              {
                "kind": "const",
                "value": [
                  109,
                  101,
                  114,
                  99,
                  104,
                  97,
                  110,
                  116
                ]
              },
              {
                "kind": "account",
                "path": "authority"
              }
            ]
          }
        },
        {
          "name": "authority",
          "writable": true,
          "signer": true
        },
        {
          "name": "system_program",
          "address": "11111111111111111111111111111111"
        }
      ],
      "args": [
        {
          "name": "name",
          "type": "string"
        }
      ]
    },
    {
      "name": "renew_entitlement",
      "discriminator": [
        184,
        110,
        22,
        31,
        98,
        31,
        246,
        52
      ],
      "accounts": [
        {
          "name": "merchant_config",
          "pda": {
            "seeds": [
              {
                "kind": "const",
                "value": [
                  109,
                  101,
                  114,
                  99,
                  104,
                  97,
                  110,
                  116
                ]
              },
              {
                "kind": "account",
                "path": "authority"
              }
            ]
          }
        },
        {
          "name": "plan",
          "pda": {
            "seeds": [
              {
                "kind": "const",
                "value": [
                  112,
                  108,
                  97,
                  110
                ]
              },
              {
                "kind": "account",
                "path": "merchant_config"
              },
              {
                "kind": "account",
                "path": "plan.plan_id",
                "account": "Plan"
              }
            ]
          }
        },
        {
          "name": "entitlement",
          "writable": true,
          "pda": {
            "seeds": [
              {
                "kind": "const",
                "value": [
                  101,
                  110,
                  116,
                  105,
                  116,
                  108,
                  101,
                  109,
                  101,
                  110,
                  116
                ]
              },
              {
                "kind": "account",
                "path": "merchant_config"
              },
              {
                "kind": "account",
                "path": "plan.plan_id",
                "account": "Plan"
              },
              {
                "kind": "account",
                "path": "entitlement.subscriber",
                "account": "Entitlement"
              }
            ]
          }
        },
        {
          "name": "authority",
          "signer": true,
          "relations": [
            "merchant_config"
          ]
        }
      ],
      "args": [
        {
          "name": "payment_reference_hash",
          "type": {
            "array": [
              "u8",
              32
            ]
          }
        },
        {
          "name": "amount_usd_cents",
          "type": "u64"
        }
      ]
    },
    {
      "name": "revoke_entitlement",
      "discriminator": [
        90,
        39,
        6,
        171,
        244,
        7,
        246,
        176
      ],
      "accounts": [
        {
          "name": "merchant_config",
          "pda": {
            "seeds": [
              {
                "kind": "const",
                "value": [
                  109,
                  101,
                  114,
                  99,
                  104,
                  97,
                  110,
                  116
                ]
              },
              {
                "kind": "account",
                "path": "authority"
              }
            ]
          }
        },
        {
          "name": "entitlement",
          "writable": true,
          "pda": {
            "seeds": [
              {
                "kind": "const",
                "value": [
                  101,
                  110,
                  116,
                  105,
                  116,
                  108,
                  101,
                  109,
                  101,
                  110,
                  116
                ]
              },
              {
                "kind": "account",
                "path": "merchant_config"
              },
              {
                "kind": "account",
                "path": "entitlement.plan_id",
                "account": "Entitlement"
              },
              {
                "kind": "account",
                "path": "entitlement.subscriber",
                "account": "Entitlement"
              }
            ]
          }
        },
        {
          "name": "authority",
          "signer": true,
          "relations": [
            "merchant_config"
          ]
        }
      ],
      "args": []
    },
    {
      "name": "update_plan",
      "discriminator": [
        119,
        112,
        58,
        60,
        76,
        205,
        1,
        100
      ],
      "accounts": [
        {
          "name": "merchant_config",
          "pda": {
            "seeds": [
              {
                "kind": "const",
                "value": [
                  109,
                  101,
                  114,
                  99,
                  104,
                  97,
                  110,
                  116
                ]
              },
              {
                "kind": "account",
                "path": "authority"
              }
            ]
          }
        },
        {
          "name": "plan",
          "writable": true,
          "pda": {
            "seeds": [
              {
                "kind": "const",
                "value": [
                  112,
                  108,
                  97,
                  110
                ]
              },
              {
                "kind": "account",
                "path": "merchant_config"
              },
              {
                "kind": "account",
                "path": "plan.plan_id",
                "account": "Plan"
              }
            ]
          }
        },
        {
          "name": "authority",
          "signer": true,
          "relations": [
            "merchant_config"
          ]
        }
      ],
      "args": [
        {
          "name": "name",
          "type": {
            "option": "string"
          }
        },
        {
          "name": "price_usd_cents",
          "type": {
            "option": "u64"
          }
        },
        {
          "name": "period_days",
          "type": {
            "option": "u16"
          }
        },
        {
          "name": "active",
          "type": {
            "option": "bool"
          }
        }
      ]
    }
  ],
  "accounts": [
    {
      "name": "Entitlement",
      "discriminator": [
        220,
        250,
        27,
        244,
        55,
        49,
        74,
        154
      ]
    },
    {
      "name": "MerchantConfig",
      "discriminator": [
        184,
        154,
        125,
        252,
        112,
        73,
        0,
        144
      ]
    },
    {
      "name": "Plan",
      "discriminator": [
        161,
        231,
        251,
        119,
        2,
        12,
        162,
        2
      ]
    }
  ],
  "errors": [
    {
      "code": 6000,
      "name": "InvalidAuthority",
      "msg": "Invalid authority: caller is not the merchant"
    },
    {
      "code": 6001,
      "name": "PlanInactive",
      "msg": "Plan is inactive"
    },
    {
      "code": 6002,
      "name": "WrongMerchant",
      "msg": "Entitlement belongs to wrong merchant or plan"
    },
    {
      "code": 6003,
      "name": "AlreadyActive",
      "msg": "Entitlement already active for this subscriber"
    },
    {
      "code": 6004,
      "name": "UnauthorizedRevocation",
      "msg": "Unauthorized: only merchant can revoke"
    },
    {
      "code": 6005,
      "name": "NameTooLong",
      "msg": "Name exceeds 64 character limit"
    },
    {
      "code": 6006,
      "name": "InvalidPrice",
      "msg": "Price must be greater than zero"
    },
    {
      "code": 6007,
      "name": "InvalidPeriod",
      "msg": "Period must be greater than zero days"
    }
  ],
  "types": [
    {
      "name": "Entitlement",
      "type": {
        "kind": "struct",
        "fields": [
          {
            "name": "merchant",
            "type": "pubkey"
          },
          {
            "name": "plan",
            "type": "pubkey"
          },
          {
            "name": "plan_id",
            "type": "u64"
          },
          {
            "name": "subscriber",
            "type": "pubkey"
          },
          {
            "name": "active",
            "type": "bool"
          },
          {
            "name": "starts_at",
            "type": "i64"
          },
          {
            "name": "expires_at",
            "type": "i64"
          },
          {
            "name": "payment_reference_hash",
            "type": {
              "array": [
                "u8",
                32
              ]
            }
          },
          {
            "name": "last_payment_amount_usd_cents",
            "type": "u64"
          },
          {
            "name": "bump",
            "type": "u8"
          }
        ]
      }
    },
    {
      "name": "MerchantConfig",
      "type": {
        "kind": "struct",
        "fields": [
          {
            "name": "authority",
            "type": "pubkey"
          },
          {
            "name": "receiver",
            "type": "pubkey"
          },
          {
            "name": "name",
            "type": "string"
          },
          {
            "name": "plan_count",
            "type": "u64"
          },
          {
            "name": "bump",
            "type": "u8"
          }
        ]
      }
    },
    {
      "name": "Plan",
      "type": {
        "kind": "struct",
        "fields": [
          {
            "name": "merchant",
            "type": "pubkey"
          },
          {
            "name": "plan_id",
            "type": "u64"
          },
          {
            "name": "name",
            "type": "string"
          },
          {
            "name": "price_usd_cents",
            "type": "u64"
          },
          {
            "name": "period_days",
            "type": "u16"
          },
          {
            "name": "active",
            "type": "bool"
          },
          {
            "name": "created_at",
            "type": "i64"
          },
          {
            "name": "bump",
            "type": "u8"
          }
        ]
      }
    }
  ]
}